{
  "country_iso3": "UKR",
  "date_start": "2017-01-01",
  "date_end": "2025-12-31",
  "n_calendar_days": 3287,
  "n_trading_days_fx": 3286,
  "data_coverage_pct": 99.97,
  "first_date_with_fx": "2017-01-02",
  "last_date_with_fx": "2025-12-31",
  "max_consecutive_gap_days": 1,
  "fx_first": 26.907,
  "fx_last": 41.99762,
  "fx_min": 22.946453,
  "fx_max": 42.237263,
  "total_depreciation_pct": 56.0844,
  "max_30d_depreciation_pct": 26.072,
  "max_30d_appreciation_pct": -9.8853,
  "mean_vol_30d": 0.004909,
  "max_vol_30d": 0.037529,
  "annualised_vol_pct": 9.5358,
  "crisis_threshold_pct": 5.0,
  "n_crisis_days_30d": 189,
  "crisis_coverage_pct": 5.83,
  "oil_mean_usd": 70.4543,
  "yield_us10y_mean": 2.7898,
  "date_max_30d_depreciation": "2022-08-29",
  "date_max_30d_appreciation": "2018-03-09"
}