{
  "country_iso3": "CHL",
  "date_start": "2017-01-01",
  "date_end": "2025-12-31",
  "n_calendar_days": 3287,
  "n_trading_days_fx": 3286,
  "data_coverage_pct": 99.97,
  "first_date_with_fx": "2017-01-02",
  "last_date_with_fx": "2025-12-31",
  "max_consecutive_gap_days": 1,
  "fx_first": 668.599976,
  "fx_last": 914.25,
  "fx_min": 581.099976,
  "fx_max": 1050.26001,
  "total_depreciation_pct": 36.741,
  "max_30d_depreciation_pct": 29.4511,
  "max_30d_appreciation_pct": -16.0198,
  "mean_vol_30d": 0.009633,
  "max_vol_30d": 0.028598,
  "annualised_vol_pct": 15.483,
  "crisis_threshold_pct": 5.0,
  "n_crisis_days_30d": 398,
  "crisis_coverage_pct": 12.27,
  "oil_mean_usd": 70.4543,
  "yield_us10y_mean": 2.7898,
  "date_max_30d_depreciation": "2022-07-18",
  "date_max_30d_appreciation": "2022-08-30"
}