{
  "full_auc": 0.8507,
  "n_features": 9,
  "feature_names": [
    "spi_30d",
    "chirps_7d_anom_pct",
    "era5_soil_moisture_day0",
    "era5_soil_moisture_deep_day0",
    "era5_soil_moisture_deep_7d_mean",
    "gpm_peak_3h_mm",
    "jrc_recurrence_pct",
    "pop_density_km2",
    "terrain_slope_mean"
  ],
  "leave_one_out": {
    "spi_30d": {
      "auc_without": 0.8457,
      "auc_drop": 0.005
    },
    "chirps_7d_anom_pct": {
      "auc_without": 0.8515,
      "auc_drop": -0.0008
    },
    "era5_soil_moisture_day0": {
      "auc_without": 0.847,
      "auc_drop": 0.0037
    },
    "era5_soil_moisture_deep_day0": {
      "auc_without": 0.8495,
      "auc_drop": 0.0011
    },
    "era5_soil_moisture_deep_7d_mean": {
      "auc_without": 0.8484,
      "auc_drop": 0.0023
    },
    "gpm_peak_3h_mm": {
      "auc_without": 0.8399,
      "auc_drop": 0.0108
    },
    "jrc_recurrence_pct": {
      "auc_without": 0.8477,
      "auc_drop": 0.003
    },
    "pop_density_km2": {
      "auc_without": 0.8334,
      "auc_drop": 0.0173
    },
    "terrain_slope_mean": {
      "auc_without": 0.8501,
      "auc_drop": 0.0006
    }
  },
  "single_feature": {
    "spi_30d": 0.6388,
    "chirps_7d_anom_pct": 0.6613,
    "era5_soil_moisture_day0": 0.7421,
    "era5_soil_moisture_deep_day0": 0.7261,
    "era5_soil_moisture_deep_7d_mean": 0.7025,
    "gpm_peak_3h_mm": 0.6802,
    "jrc_recurrence_pct": 0.6267,
    "pop_density_km2": 0.6952,
    "terrain_slope_mean": 0.6275
  }
}